Workbook

Sheet Automation Regression Test Plan
A1: Automation | B1: CR Related | C1: Test Case ID | D1: Priority | E1: Tester | F1: Category | G1: Account Type | H1: Product | I1: Test Case Description | J1: Test Case Steps | K1: Expected Result
A2: Not Automated | B2: 25 | C2: RT.1 | D2: High | F2: Personal | G2: Client Maintenance | I2: Document Manager | J2: 1. Search existing Client with DOB over 18, Tax ID type of "ATIN" and Tax ID number 2. Navigate to the Client Profile and choose Maintenance in Connects 3. Enter new name and validate popup a. Pop up displayed titled "Caution" b. Text displayed “Verify the customer’s ID. If non-identification documentation (e.g., divorce decree) is presented, upload through Document Access”. d. After OK, Message closed, user returned to window with focus on next available field 4. Update Address, Tax ID type/number and phone number | K2: 1. Validate TIN type and number are blanked out (ATIN only eligible for clients under 18 years of age)
A3: Not Automated | B3: 25 | C3: RT.2 | D3: High | F3: Personal | G3: Client Maintenance | I3: Document Manager | J3: 5. Navigate to Document Manager | K3: 1. Validate Customer Information Change form and W-9 generated with all fields mapped
A4: Not Automated | B4: 25 | C4: RT.3 | D4: High | F4: Personal | G4: Client Maintenance | I4: Client Profile - Connects | J4: 6. Validate Client and Account level (account that had address change) caution generated 7. End Session a. Choose OK on warning b. End Session again - validate session ends as normal. | K4: 1. Caution displays with text of "Address changed in last 31 days on related client, account or portfolio. Ensure you have identified the client properly." 2. Validate end session warning popup displays: a. Title = High Risk Change b. Text = "Changing the Address and E-Mail Address is considered High Risk. Ensure you have identified the client properly."
A5: Not Automated | B5: 25 | C5: RT.4 | D5: High | F5: Personal | G5: Client Maintenance | I5: Client Profile - Navigator | J5: 8. View client and account profile in Navigator | K5: 1. Validate name, address, TIN and phone number are the only fields that updated on the client record. a. Validate the primary phone mapped to both the field selected and the home phone field b. Validate Individual mapped to the Customer Type flex field 2. Validate address changed on selected account 3. Validate Caution did NOT map to client/Account level
A6: Not Automated | B6: 25 | C6: RT.5 | D6: High | F6: Personal | G6: Client Maintenance | I6: Client Profile - Maintenance Screen | J6: 1. Navigate to existing test customer with an existing alternate name and an employer of "Minor" that is over the age of 18 in Connects (must have last name of Customer) 2. Choose Pencil icon to maintenance the client record 3. Add a new alternate name to the client 4. Enter new valid Employer (not "Minor") 5. Complete all other required fields and save changes | K6: 1. Validate all fields on client record pulled in correctly into maintenance fields in Connects a. Exception: ID, Employer or Occupation containing Minor should be blanked out if the client's age is over 18. Validate Employer field is not populated.
A7: Not Automated | B7: 25 | C7: RT.6 | D7: High | F7: Personal | G7: Client Maintenance | I7: Document Manager | J7: 6. Navigate to Document Manager | K7: 1. Validate Customer Information Change form generated with all fields mapped
A8: Not Automated | B8: 25 | C8: RT.7 | D8: High | F8: Personal | G8: Client Maintenance | I8: Client Profile - Navigator | J8: 7. View client profile in Navigator | K8: 1. Validate new alternate name was added and existing alternate name was not removed 2. Validate "Individual" mapped to the Client Type flex field 3. Validate new Employer mapped as entered 4. Validate any other changed fields mapped
A9: Not Automated | B9: 25 | C9: RT.8 | D9: High | F9: Personal | G9: Client Maintenance | I9: Client Profile - Maintenance Screen | J9: 1. Navigate to existing test customer with an existing alternate name and an employer of "Minor" that is over the age of 18 in Connects (must have last name of Customer) 2. Choose Pencil icon to maintenance the client record 3. Change Country of Citizenship to a Non-US country a. Select No to Permanent Resident, Government-Issued Visas and Resident Alien for Tax Reporting questions 4. Add a new alternate name to the client 5. Enter new valid Employer (not "Minor") | K9: 1. Validate all fields on client record pulled in correctly into maintenance fields in Connects a. Exception: ID, Employer or Occupation containing Minor should be blanked out if the client's age is over 18. Validate Employer field is not populated.
A10: Not Automated | B10: 25 | C10: RT.9 | D10: High | F10: Personal | G10: Client Maintenance | I10: Document Manager | J10: 5. Navigate to Document Manager | K10: 1. Validate Customer Information Change form, W-9 and W-8 Ben generated with all fields mapped
A11: Not Automated | B11: 25 | C11: RT.10 | D11: High | F11: Personal | G11: Client Maintenance | I11: Client Profile - Navigator | J11: 6. View client profile in Navigator | K11: 1. Validate new alternate name was added and existing alternate name was not removed 2. Validate "Individual" mapped to the Client Type flex field 3. Validate new Employer mapped as entered 4. Validate new Country of Citizenship mapped to flex field
A12: Not Automated | B12: 25 | C12: RT.11 | D12: High | F12: Personal | G12: Client Maintenance | I12: Client Profile - Navigator | J12: 7. View client profile in Navigator and navigate to the Foreign Codes section | K12: 1. N maps to “U.S. Government Issued Visas?” flex field #33 in Nav 2. “N” maps to “Resident Alien for Tax Reporting” flex field #39 in Nav 3. “[1]” (Nonresident Alien High-Risk) displays in “Residency Status” field in Nav. 4. "N" maps to U.S. Permanent Resident Card flex field 5. "1042-S and W-8 Reporting" maps to "Foreign Code" field 6. "W-8 Beneficiary" maps to "W-8 Form Type" field 7. Current date maps to "Certification Date" host field 8. 3 years from the current date maps to the "Expiration Date" host field 9. "[29] Deposit Interest" maps to "Income Code" field 10. "[5] US Withholding Agent - FI" maps to "Chapter 3 Status Code" field 11. 2-digit country of citizenship abbreviation maps to "Country Residence Code" field 12. 2-digit country of citizenship abbreviation maps to "Country Tax Code" field 13. "Chapter 3 (NRA and Foreign Corporations)" maps to "Withholding Type' field
A13: Not Automated | B13: 35 | C13: RT.12 | D13: High | F13: Personal | G13: DDA | H13: Freestyle Checking | I13: Print TIS Only | J13: 1. Without a client in session, navigate to "Product Search" in Connects. 2. On a Freestyle checking account, select "Print TIS Only" 3. Validate a new Print window displays with the Freestyle Truth in Savings (not Document Manager) and print to PDF for testing purposes | K13: 1. Validate all mapping on the Freestyle Truth in Savings: a. Date Opened/As of = Curent Date b. Customer Name = For Informational Purposes Only c. Account Number = Blank d. Product = Freestyle checking e. Minimum Balance = blank or zero
A14: Not Automated | B14: 35 | C14: RT.13 | D14: High | F14: Personal | G14: DDA | H14: Health Savings - Individual Checking | I14: Print TIS Only | J14: 1. Without a client in session, navigate to "Product Search" in Connects. 2. On a Health Savings - Individual checking account, select "Print TIS Only" 3. Validate a new Print window displays with the Health Savings - Individual Truth in Savings (not Document Manager) and print to PDF for testing purposes | K14: 1. Validate all mapping on the Health Savings - Individual Truth in Savings: a. Date Opened/As of = current Date b. Customer Name = For Informational Purposes Only c. Account Number = Blank d. Product = Health Savings - Individual checking e.. Minimum Balance = blank or zero f. Rate and APY match to the current rate sheet for the region (APY rounded up to two decimal places)
A15: Not Automated | B15: 35 | C15: RT.14 | D15: High | F15: Personal | G15: DDA | H15: Firstrate Money Market Checking | I15: Print TIS Only | J15: 1. Without a client in session, navigate to "Product Search" in Connects. 2. On a Firstrate Money Market checking account, select "Print TIS Only" 3. Validate a new Print window displays with the Firstrate Money Market Truth in Savings (not Document Manager) and print to PDF for testing purposes | K15: 1. Validate all mapping on the Firstrate Money Market Truth in Savings: a. Date Opened/As of = current Date b. Customer Name = For Informational Purposes Only c. Account Number = Blank d. Product = Firstrate Money Market checking e. Rate and APY match to the current rate sheet for the region (APY rounded up to two decimal places)
A16: Not Automated | B16: 35 | C16: RT.15 | D16: High | F16: Personal | G16: SAV | H16: FirstRate Savings | I16: Print TIS Only | J16: 1. Without a client in session, navigate to "Product Search" in Connects. 2. On a FirstRate Savings account, select "Print TIS Only" 3. Validate a new Print window displays with the First Rate Savings Truth in Savings (not Document Manager) and print to PDF for testing purposes | K16: 1. Validate all mapping on the FirstRate Savings Truth in Savings: a. Date Opened/As of = Curent Date b. Customer Name = For Informational Purposes Only c. Account Number = Blank d. Product = FirstRate Savings e. Rate and APY match to the current rate sheet for the region (APY rounded up to two decimal places) f. Minimum Balance = blank or zero
A17: Not Automated | B17: 35 | C17: RT.16 | D17: High | F17: Personal | G17: SAV | H17: Saver's Goal CD | I17: Print TIS Only | J17: 1. Without a client in session, navigate to "Product Search" in Connects. 2. On a Saver's Goal CD account, select "Print TIS Only" 3. Validate a new Print window displays with the Regular CD Savings Truth in Savings (not Document Manager) and print to PDF for testing purposes | K17: 1. Validate all mapping on the Regular CD Truth in Savings: a. Date Opened/As of = current Date b. Customer Name = For Informational Purposes Only c. Account Number = Blank d. Product = Saver's Goal CD e. Issue Date = Blank f. Rate and APY match to the current rate sheet for the region (APY rounded up to two decimal places) g. "The minimum deposit to a Savers Goal CD is $25.00..." checkbox is selected h. "Automatically Renewable Time Account" checkbox selected
A18: Not Automated | B18: 35 | C18: RT.17 | D18: High | F18: Personal | G18: COD | H18: 18-23 MO CD | I18: Print TIS Only | J18: 1. Without a client in session, navigate to "Product Search" in Connects. 2. On a 18-23 MO CD account, select "Print TIS Only" 3. Validate a new Print window displays with the Regular CD Truth in Savings (not Document Manager) and print to PDF for testing purposes | K18: 1. Validate all mapping on the Regular CD Truth in Savings: a. Date Opened/As of = Curent Date b. Customer Name = For Informational Purposes Only c. Account Number = Blank d. Product = 18-23 MO CD e. Issue Date = Blank f. Rate and APY match to the current rate sheet for the region (APY rounded up to two decimal places) g. Minimum Balance = $500 (must be configured in CBRM as such) h. "You may not make any deposits into your account before maturity..." checkbox selected i. "Automatically Renewable Time Account" checkbox selected
A19: Not Automated | B19: 35 | C19: RT.18 | D19: High | F19: Personal | G19: COD | H19: 35 Month CD Special | I19: Print TIS Only | J19: 1. Without a client in session, navigate to "Product Search" in Connects. 2. On a 35 Month CD Special account, select "Print TIS Only" 3. Validate a new Print window displays with the Special CD Truth in Savings (not Document Manager) and print to PDF for testing purposes | K19: 1. Validate all mapping on the Special CD Truth in Savings: a. Date Opened/As of = Curent Date b. Customer Name = For Informational Purposes Only c. Account Number = Blank d. Product = 35 Month CD Special e. Issue Date = Blank f. Rate and APY match to the current rate sheet for the region (APY rounded up to two decimal places) g. Minimum Balance = $5,000 (must be configured in CBRM as such) h. Maximum Balance = $100,000 (must be configured in CBRM) i. "You may not make any deposits into your account before maturity..." checkbox selected j. "Automatically Renewable Time Account" checkbox selected
A20: Not Automated | B20: 35 | C20: RT.19 | D20: High | F20: Personal | G20: SAV | H20: IRA Savings | I20: Print TIS Only | J20: 1. Without a client in session, navigate to "Product Search" in Connects. 2. On a IRA Savings account, select "Print TIS Only" 3. Validate a new Print window displays with the IRA Savings Truth in Savings (not Document Manager) and print to PDF for testing purposes | K20: 1. Validate all mapping on the IRA Savings Truth in Savings: a. Date Opened/As of = current Date b. Customer Name = For Informational Purposes Only c. Account Number = Blank d. Product = IRA Savings e. Rate and APY match to the current rate sheet for the region (APY rounded up to two decimal places)
A21: Not Automated | B21: 35 | C21: RT.20 | D21: High | F21: Personal | G21: COD-IRA | H21: 6-11 MO IRA | I21: Print TIS Only | J21: 1. Without a client in session, navigate to "Product Search" in Connects. 2. On a 6-11 MO IRA account, select "Print TIS Only" 3. Validate a new Print window displays with the Regular CD Truth in Savings (not Document Manager) and print to PDF for testing purposes | K21: 1. Validate all mapping on the Regular CD Truth in Savings: a. Date Opened/As of = Curent Date b. Customer Name = For Informational Purposes Only c. Account Number = Blank d. Product = 6-11 MO IRA e. Issue Date = Blank f. Rate and APY match to the current rate sheet for the region (APY rounded up to two decimal places) g. Minimum Balance = $500 (must be configured in CBRM as such) h. "You may not make any deposits into your account before maturity..." checkbox selected i. "Automatically Renewable Time Account" checkbox selected
A22: Not Automated | B22: 35 | C22: RT.21 | D22: High | F22: Personal | G22: COD-IRA | H22: 7 MO IRA Special | I22: Print TIS Only | J22: 1. Without a client in session, navigate to "Product Search" in Connects. 2. On a 7 MO IRA Special account, select "Print TIS Only" 3. Validate a new Print window displays with the Special CD Truth in Savings (not Document Manager) and print to PDF for testing purposes | K22: 1. Validate all mapping on the Special CD Truth in Savings: a. Date Opened/As of = Curent Date b. Customer Name = For Informational Purposes Only c. Account Number = Blank d. Product = 7 MO IRA Special e. Issue Date = Blank f. Rate and APY match to the current rate sheet for the region (APY rounded up to two decimal places) g. Minimum Balance = $10,000 (must be configured in CBRM as such) h. Maximum Balance = $100,000 (must be configured in CBRM) i. "You may not make any deposits into your account before maturity..." checkbox selected j. "Automatically Renewable Time Account" checkbox selected
A23: Not Automated | B23: 35 | C23: RT.22 | D23: High | F23: Business | G23: COD | H23: 18-23 MO CD | I23: Print TIS Only | J23: 1. Without a client in session, navigate to "Product Search" in Connects and choose Business. 2. On a 18-23 MO CD account, select "Print TIS Only" 3. Validate a new Print window displays with the Regular CD Truth in Savings (not Document Manager) and print to PDF for testing purposes | K23: 1. Validate all mapping on the Regular CD Truth in Savings: a. Date Opened/As of = Curent Date b. Customer Name = For Informational Purposes Only c. Account Number = Blank d. Product = 18-23 MO CD e. Issue Date = Blank f. Rate and APY match to the current rate sheet for the region (APY rounded up to two decimal places) g. Minimum Balance = $500 (must be configured in CBRM as such) h. "You may not make any deposits into your account before maturity..." checkbox selected i. "Automatically Renewable Time Account" checkbox selected
A24: Not Automated | B24: 35 | C24: RT.23 | D24: High | F24: Business | G24: COD | H24: 35 Month CD Special | I24: Print TIS Only | J24: 1. Without a client in session, navigate to "Product Search" in Connects and choose Business. 2. On a 35 Month CD Special account, select "Print TIS Only" 3. Validate a new Print window displays with the Special CD Truth in Savings (not Document Manager) and print to PDF for testing purposes | K24: 1. Validate all mapping on the Special CD Truth in Savings: a. Date Opened/As of = Curent Date b. Customer Name = For Informational Purposes Only c. Account Number = Blank d. Product = 35 Month CD Special e. Issue Date = Blank f. Rate and APY match to the current rate sheet for the region (APY rounded up to two decimal places) g. Minimum Balance = $5,000 (must be configured in CBRM as such) h. Maximum Balance = $100,000 (must be configured in CBRM) i. "You may not make any deposits into your account before maturity..." checkbox selected j. "Automatically Renewable Time Account" checkbox selected
... A38: Not Automated | B38: 3 | C38: RT.37 | D38: Medium | F38: Stop Payment | G38: DDA | H38: Any Business | I38: FNB Bill Pay Stop Pay | J38: 1. Navigate to a test client Business DDA profile in Connects 2. Select FNB Bill Pay as the type | K38: 1. Validate helper text displays: "FNB Bill Stop Payment Request must be completed by FNB Customer Service. Please call Customer Service with the customer or direct them to the Customer Service line at : 1-800-555-5455" 3. Validate Stop Payment Agreement generated in Document Manager with all fields mapped a. Choose "Automatically Mail to Customer" for the Stop Pay Agreement, validate it archives in Director
A39: Not Automated | B39: 24/7 | C39: RT.38 | D39: High | F39: New Client_Personal | G39: Personal Client Setup | I39: Client Setup - US Citizen | J39: 1. Add New Client over 18 yrs/US Citizen 2. Complete Communication Preferences 3. Select "Residence" for address 4. Use the letters "PO" in address line 1 5. Choose a phone type other than "home" 6. Enter an email address 7. Use Driver's License as the ID type 8. Complete setup | K39: 1. Validate Residential address a. Country field of address window read only and disabled b. PO box not accepted as residence 2. Validate ChexSystems triggers and if response is Review or Decline, Supervisor Override is required a. Validate "N" is passed to "eStyle Eligible Only" flex field for client
A40: Not Automated | B40: 24 | C40: RT.39 | D40: High | F40: New Client_Personal | G40: Personal Client Setup | I40: Client Setup - US Citizen | J40: 9. View Client Profile in Navigator 10. In Connects, navigate to Document Manager | K40: 1. Validate data mapped to Navigator as entered: First Name Middle Name Last Name Suffix DOB Mailing Address Physical Address Primary Phone # entered w/no type maps to "home" in Nav Mobile phone Email address Tax ID Type Tax ID# Primary ID Type – Drivers Lisc State Issue Date Number Expiration Date Employer Occupation Individual maps to flex field 13 Current date maps to "Data Residency Question Answered" flex field 30 2. Validate no documents generated in Document Manager
A41: Not Automated | B41: 24/7 | C41: RT.40 | D41: High | F41: New Client_Personal | G41: Personal Client Setup | I41: Client Setup - Non-US Citizen | J41: 1. Create New Client: 2. Select Canada as the Country of Citizenship 3. N to Are you a Resident Alien for tax reporting purposes? 4. Enter Foreign Postal Code 5. Do not enter Foreign Tax ID 6. Select Canadian Province from DDLB 7. Select Canadian DL as ID Type 8. Complete Set Up | K41: 1. Tax Rate DDLB displayed under "Foreign Tax Identification Number" field 2. 0.00% only option available in Tax Rate DDLB 3. Foreign Postal Code is not required and displays under Tax Rate field 4. Foreign Tax Identification Number is not required and displays under Foreign Postal Code field 5. Canadian Province is required and displays under Foreign Tax Identification Number field 6. Validate ChexSystems triggers and if response is Review or Decline, Supervisor Override is required a. Validate "N" is passed to "eStyle Eligible Only" flex field for client
A42: Not Automated | B42: 24 | C42: RT.41 | D42: High | F42: New Client_Personal | G42: Personal Client Setup | I42: Client Setup - Non-US Citizen | J42: 9. View Client Profile in Navigator 10. In Connects, navigate to Document Manager | K42: 1. Validate data mapped to Navigator as entered: First Name Middle Name Last Name Suffix DOB Mailing Address Physical Address Primary Phone # entered w/no type maps to "home" in Nav Mobile phone Email address Tax ID Type Tax ID# Primary ID Type – Canadian DL Province Issue Date Number Expiration Date Employer Occupation Individual maps to flex field 13 Current date maps to "Data Residency Question Answered" flex field 30 2. 0% mapped to Tax Rate field 3. N maps to “U.S. Government Issued Visas?” flex field #33 in Nav 4. “Y” maps to “Resident Alien for Tax Reporting” flex field #39 in Nav 5. “[2]” (Resident Alien) displays in “Residency Status” field in Nav. 6. "N" maps to U.S. Permanent Resident Card flex field 7. [4] Exempt under tax treaty mapped to Exemption Code field 8. Foreign Postal Code maps to "Postal Code" field 9. Nothing maps to "Foreign Tax Identification Number" field 10. Canadian Province maps to "Province Code" field 11. "1042-S and W-8 Reporting" maps to "Foreign Code" field 12. "W-8 Beneficiary" maps to "W-8 Form Type" field 13. Current date maps to "Certification Date" host field 14. 3 years from the current date maps to the "Expiration Date" host field 15. "[29] Deposit Interest" maps to "Income Code" field 16. "[5] US Withholding Agent - FI" maps to "Chapter 3 Status Code" field 17. 2-digit country of citizenship abbreviation maps to "Country Residence Code" field 18. 2-digit country of citizenship abbreviation maps to "Country Tax Code" field 19. "Chapter 3 (NRA and Foreign Corporations)" maps to "Withholding Type' field 20. Validate W-9 and W-8 Ben generated in Document Manager with all fields mapped
A43: Not Automated | B43: 8 | C43: RT.42 | D43: Medium | F43: Quicksell | G43: Personal Client Setup | I43: Client Setup with Quicksell Offer | J43: 1. Create client with a pre-approved credit card offer 2. After creating, validate Product Search from LHN | K43: 1. Megaphone icon displayed next to "product search" option 2. When hovered over icon, tool tip "special offer" label displayed
A44: Not Automated | B44: 8 | C44: RT.43 | D44: Medium | F44: Quicksell | G44: Personal Client Setup | I44: Client Setup with Quicksell Offer | J44: 3. Open Product Search for client with offers 4. Select Setup, special offer should be the first product prompted 5. Select "offered" product, validate disclosure URL opens a. Select "Yes" button and validate message and special offer window close and the offer is removed from Product Selection Grid | K44: 1. Validate Special offer pop up display text 2. Product name displayed as returned in the ChexSystems response 3. Credit limit displayed as returned in the ChexSystems response 4. Rate displayed as returned in the ChexSystems response a. Display as “Prime + [Rate]%”
A45: Not Automated | B45: 8 | C45: RT.44 | D45: Medium | F45: Quicksell | G45: Personal Client Setup | I45: Client Setup with Quicksell Offer | J45: 6. Validate quicksell offer is in DWF queue for client | K45: 1. Right-click on form in Director, choose Keywords and validate the following keywords are mapped accurately: a. Tax ID Number = customers TIN with no spaces/dashes b. Reference Number = Alphanumeric offer code from Chexsystems with no spaces/dashes c. Miscellaneous Keyword 1 = "Y"
A46: Not Automated | B46: 8 | C46: RT.45 | D46: Medium | F46: Quicksell | G46: Personal Client Setup | I46: Client Setup with Quicksell Offer | J46: 7. Validate info written to Argo Database for client | K46: 1. Validate with Business Systems Analysis (Joe Renfro, Jason Miller, etc.) that the following info was written to the Offer_Disposition database: a. CIF # b. Accepted c. Offer Date
A47: Not Automated | B47: 8 | C47: RT.46 | D47: Medium | F47: Quicksell | G47: Personal Client Maintenance | I47: Client Maintenance with Quicksell Offer | J47: 1. Add new client with credit card offer to existing account 2. Complete account maintenance 3. Disposition ChexSystems offer by choosing Decline | K47: 1. Megaphone displays next to Product Selection Left-Hand Navigation 2. Maintenance allowed before offer dispositioned 3. Offer form archives to Director with N in Offer Accepted
A48: Not Automated | B48: 8 | C48: RT.47 | D48: Medium | F48: Quicksell | G48: Personal Client Maintenance | I48: Client Maintenance with Quicksell Offer | J48: 4. Validate quicksell offer is not in DWF queue | K48: 1. Right-click on form in Director, choose Keywords and validate the following keywords are mapped accurately: a. Tax ID Number = customers TIN with no spaces/dashes b. Reference Number = Alphanumeric offer code from Chexsystems with no spaces/dashes c. Miscellaneous Keyword 1 = "N"
A49: Not Automated | B49: 8 | C49: RT.48 | D49: Medium | F49: Quicksell | G49: Personal Client Maintenance | I49: Client Maintenance with Quicksell Offer | J49: 5. Validate info written to Argo Database | K49: 1. Validate with Business Systems Analysis (Joe Renfro, Jason Miller, etc.) that the following info was written to the Offer_Disposition database: a. CIF # b. Declined c. Offer Date
A50: Not Automated | B50: 8 | C50: RT.49 | D50: Medium | F50: Quicksell | G50: DDA | H50: Any Personal | I50: Account Setup | J50: 1. Use two clients with credit card offers that are not an owner or owner/signer on a DDA or SAV and add to a new account in a new session (ChexSystems must prompt when client is added to account) 2. Complete Account Setup 3. Attempt to end session 4. Navigate to product search and disposition both ChexSystems offers by choosing Accept | K50: a. Megaphone displays next to Product Selection Left-Hand Navigation b. Account Setup allowed before offer dispositioned c. Unable to end session without dispositioning offer i. At End Session, display a pop-up message with a disposition reminder 1. Title = “Special Offer Available” 2. Icon = Error 3. Text = “A special offer is available that needs to be dispositioned before closing the session.” 4. Button = “OK” a. When clicked closes pop-up message 5. Offer form archives to Director with Y in Offer Accepted
A51: Not Automated | B51: 8 | C51: RT.50 | D51: Medium | F51: Quicksell | G51: DDA | H51: Any Personal | I51: Account Setup | J51: 5. Validate quicksell offer is in DWF queue for both clients | K51: 1. Right-click on form in Director, choose Keywords and validate the following keywords are mapped accurately: a. Tax ID Number = customers TIN with no spaces/dashes b. Reference Number = Alphanumeric offer code from Chexsystems with no spaces/dashes c. Miscellaneous Keyword 1 = "Y"
A52: Not Automated | B52: 8 | C52: RT.51 | D52: Medium | F52: Quicksell | G52: DDA | H52: Any Personal | I52: Account Setup | J52: 6. Validate info written to Argo Database for each client | K52: 1. Validate with Business Systems Analysis (Joe Renfro, Jason Miller, etc.) that the following info was written to the Offer_Disposition database: a. CIF # b. Accepted c. Offer Date
A53: Not Automated | B53: 8 | C53: RT.52 | D53: Medium | F53: Quicksell | G53: SAV | H53: Any Personal | I53: Account Maintenance | J53: 1. Use client with credit card offer that is not an owner or owner/signer on a DDA or SAV and add to existing account in a new session (ChexSystems must prompt when client is added to account) 2. Complete account maintenance 3. Navigate to Product Search and disposition ChexSystems offer by choosing Decline | K53: 1. Megaphone displays next to Product Selection Left-Hand Navigation 2. Maintenance allowed before offer dispositioned 3. Offer form archives to Director with N in Offer Accepted
A54: Not Automated | B54: 8 | C54: RT.53 | D54: Medium | F54: Quicksell | G54: SAV | H54: Any Personal | I54: Account Maintenance | J54: 4. Validate quicksell offer is not in DWF queue | K54: 1. Right-click on form in Director, choose Keywords and validate the following keywords are mapped accurately: a. Tax ID Number = customers TIN with no spaces/dashes b. Reference Number = Alphanumeric offer code from Chexsystems with no spaces/dashes c. Miscellaneous Keyword 1 = "N" 2. If keywords mapped correctly, validate with Director team (Kelley Redfoot, Marlee Farrell, etc.) that request is removed from QA BPM Form Processing queue
A55: Not Automated | B55: 8 | C55: RT.54 | D55: Medium | F55: Quicksell | G55: SAV | H55: Any Personal | I55: Account Maintenance | J55: 5. Validate info written to Argo Database | K55: 1. Validate with Business Systems Analysis (Joe Renfro, Jason Miller, etc.) that the following info was written to the Offer_Disposition database: a. CIF # b. Declined c. Offer Date
A56: Not Automated | B56: 15 | C56: RT.55 | D56: Medium | F56: Close Account | G56: Account Maintenance | H56: Any DDA | I56: DDA Close Account LHN | J56: 1. Search DDA Account with available balance and choose "Close Account" from Service and Maintenance left-hand navigation 2. Requested: choose "Bank" a. Select Closeout Reason of "Fraud" 3. Validate Action Items contain the following: a. "Remove Overdraft Protection if applicable" with ? hyperlink that opens the auto transfer procedure b. "Complete Debit Card Maintenance/Closing if applicable" 4. Validate Services contain the following: a. "Outstanding Checks?" i. Choose Yes and validate "Notify the customer that outstanding checks will be returned Account Closed” displays b. "FNB Bill Pay" i. Choose Yes and validate "Use the Online Banking & Digital Payment Support Request Director form to request Bill Pay be cancelled for the account." displays c. "Direct Deposit/Auto Debits/Auto Payments?" i. Choose Yes and validate "Advise the customer to provide their new account information to their employer or merchants” displays 5. Validate "Close Account" is not enabled until "Customer Information Verified?" is checked, then select the "Close Account" button 6. Select "OK" on info alert message box | K56: 1. Informational Message "Alert" displayed a."The available balance is greater than $0.00. Complete the closing withdrawal in Teller" b "OK" Button 2. Message Closes 3. "Close Account" Window Closes 4. Transaction Restriction code of 1 added to account in Nav 5. Miscellaneous Addenda (Caution) added to account with details a. a. Employee Name = Name of employee processing the “Close Account” b. Date = Current processing date c. Expiration Date = (Leave Blank) d. Caution Type = Caution e. Details = “Account Closed on MM-DD-YYYY (current processing date) per Bank request” 6. Validate all Close Account data is written to the Connects database 7. Validate "Y" passed to "Account Closed by Bank for Fraud" flex field on the account
A57: Not Automated | B57: 15 | C57: RT.56 | D57: Medium | F57: Close Account | G57: Account Maintenance | H57: Any SAV | I57: SAV Close Account LHN | J57: 1. Search SAV Account with negative balance and an automatic transfer and choose "Close Account" from Service and Maintenance left-hand navigation 2. Requested: choose "Mail" a. Validate "Call the customer and confirm they sent the request" and "Follow the Authenticating an Individual's Identity procedure for HIGH-RISK transactions" displays with a ? hyperlink to the high-risk procedure b. Select Closeout Reason 3. Validate Action Items contain the following: a. "Account has an Automatic Transfer for Payment" b. "Complete Debit Card Maintenance/Closing if applicable" 4. Validate Services contain the following: a. "Direct Deposit/Auto Debits/Auto Payments?" i. Choose No and validate nothing displays 3. Validate "Close Account" is not enabled until "Customer Information Verified?" is checked, then select the "Close Account" button 4. Select "OK" on info alert message box | K57: 1. Informational Message "Alert" displayed a. Title = "Close Account Error" b. Text = "The account cannot be closed because the Closing balance is negative. The Closing Balance must be brought to an amount greater than or equal to $0.00 to close this account" c "OK" Button 2. Message Closes 3. "Close Account" Window Closes 4. Transaction Restriction code of 1 does not map to account in Nav 5. Account Closed Miscellaneous Addenda (Caution) is not added to account in Nav
A58: Not Automated | B58: 15 | C58: RT.57 | D58: Medium | F58: Close Account | G58: Account Maintenance | H58: Any CD | I58: CD Close Account LHN | J58: 1. Search CD Account with zero balance and choose "Close Account" from Service and Maintenance left-hand navigation 2. Requested: choose "Phone" a. Validate "Follow the Authenticating an Individual's Identity procedure for HIGH-RISK transactions" displays with a ? hyperlink to the high-risk procedure b. Select Closeout Reason 3. Action Items section is hidden 4. Services section is hidden 3. Validate "Close Account" is not enabled until "Customer Information Verified?" is checked, then select the "Close Account" button 4. Select "OK" on info alert message box | K58: 1. Informational Message "Alert" displayed a. Title = "Alert - Available Balance $0.00" b. Text = "Complete the TMS entry in Navigator to close the account" c "OK" Button 2. Message Closes 3. "Close Account" Window Closes 4. Transaction Restriction code of 1 added to account in Nav 5. Miscellaneous Addenda (Caution) added to account with details a. a. Employee Name = Name of employee processing the “Close Account” b. Date = Current processing date c. Expiration Date = (Leave Blank) d. Caution Type = Caution e. Details = y “Account Closed on MM-DD-YYYY (current processing date) per Bank request” 6. Validate all Close Account data is written to the Connects database
A59: Not Automated | B59: 15 | C59: RT.58 | D59: Medium | F59: Close Account | G59: Account Maintenance | H59: Any SDB | I59: SDB Close Account LHN | J59: 1. Search SDB Account with available balance and Numerical data in Nav field for Billing Method and choose "Close Account" from Service and Maintenance left-hand navigation 2. Requested: choose "In Person" 3. In Action Items, text displayed as "Account has an Automatic Payment" 4. Services section is hidden 5. Select Closeout Reason 6. Select "Close Account" button 7. Select "OK" on info alert message box | K59: 1. Informational Message "Alert" displayed a."The available balance is greater than $0.00. Complete the closing withdrawal in Teller" b "OK" Button 2. Message Closes 3. "Close Account" Window Closes 4. Validate all Close Account data is written to the Connects database
A60: Not Automated | B60: 18 | C60: RT.59 | D60: Medium | F60: Cautions | H60: Any Test Client | I60: Client Profile - Add New Caution | J60: 1. Search client in Connects 2. View Client Profile 3. Select "add" on Cautions Card 5. Add new caution to client profile with expiration date and save 6. Search Client in Navigator | K60: 1. Validate information added in connects passes to customer level in navigator a. “Caution” text data to the “Description” host field(s) b. “Priority” to the “Priority Code:” host field c. “Responsibility Code” of the user who added caution d. “Expiration Date” to the “Expiration Date” host field 2. Validate Caution displays in Client Profile in Connects
A61: Not Automated | B61: 18 | C61: RT.60 | D61: Medium | F61: Cautions | H61: Any DDA | I61: DDA Account Profile - Add New Caution and Teller Alert | J61: 1. Search Account in Connects 2. View Account Profile in Connects 3. Select "add" on Cautions Card 4. Select "Caution" as Type 5. Add Caution with expiration date and Save 6. Select "add" again, add Caution type of "Teller Alert" and Save 7. View Account in Navigator | K61: 1. Multi-line entry required field displayed for type of "Caution" 2. Information passed to account addenda level as below: a. “Caution” text data to the “Description” host field(s) b. “Priority” to the “Priority Code:” host field c. “Responsibility Code” of the user d. Expiration Date” to the “Expiration Date” host field 3. Teller Alert passed to account in Navigator 4. Caution and Teller alert display in account profile in Connects
A62: Not Automated | B62: 18 | C62: RT.61 | D62: Medium | F62: Cautions | H62: Any SAV | I62: SAV Account Profile - Add New Caution and Teller Alert | J62: 1. Search Account in Connects 2. View Account Profile in Connects 3. Select "add" on Cautions Card 4. Select "Caution" as Type 5. Add Caution with expiration date and Save 6. Select "add" again, add Caution type of "Teller Alert" and Save 7. View Account in Navigator | K62: 1. Multi-line entry required field displayed for type of "Caution" 2. Information passed to account addenda level as below: a. “Caution” text data to the “Description” host field(s) b. “Priority” to the “Priority Code:” host field c. “Responsibility Code” of the user d. Expiration Date” to the “Expiration Date” host field 3. Teller Alert passed to account in Navigator 4. Caution and Teller alert display in account profile in Connects
A63: Not Automated | B63: 18 | C63: RT.62 | D63: Medium | F63: Cautions | H63: Any IRA SAV | I63: IRA SAV Account Profile - Add New Caution and Teller Alert | J63: 1. Search Account in Connects 2. View Account Profile in Connects 3. Select "add" on Cautions Card 4. Select "Caution" as Type 5. Add Caution with expiration date and Save 6. Select "add" again, add Caution type of "Teller Alert" and Save 7. View Account in Navigator | K63: 1. Multi-line entry required field displayed for type of "Caution" 2. Information passed to account addenda level as below: a. “Caution” text data to the “Description” host field(s) b. “Priority” to the “Priority Code:” host field c. “Responsibility Code” of the user d. Expiration Date” to the “Expiration Date” host field 3. Teller Alert passed to account in Navigator 4. Caution and Teller alert display in account profile in Connects
A64: Not Automated | B64: 18 | C64: RT.63 | D64: Medium | F64: Cautions | H64: Any CD | I64: CD Account Profile - Add New Caution and Teller Alert | J64: 1. Search Account in Connects 2. View Account Profile in Connects 3. Select "add" on Cautions Card 4. Select "Caution" as Type 5. Add Caution with expiration date and Save 6. Select "add" again, add Caution type of "Teller Alert" and Save 7. View Account in Navigator | K64: 1. Multi-line entry required field displayed for type of "Caution" 2. Information passed to account addenda level as below: a. “Caution” text data to the “Description” host field(s) b. “Priority” to the “Priority Code:” host field c. “Responsibility Code” of the user d. Expiration Date” to the “Expiration Date” host field 3. Teller Alert passed to account in Navigator 4. Caution and Teller alert display in account profile in Connects
A65: Not Automated | B65: 18 | C65: RT.64 | D65: Medium | F65: Cautions | H65: Any IRA CD | I65: IRA CD Account Profile - Add New Caution and Teller Alert | J65: 1. Search Account in Connects 2. View Account Profile in Connects 3. Select "add" on Cautions Card 4. Select "Caution" as Type 5. Add Caution with expiration date and Save 6. Select "add" again, add Caution type of "Teller Alert" and Save 7. View Account in Navigator | K65: 1. Multi-line entry required field displayed for type of "Caution" 2. Information passed to account addenda level as below: a. “Caution” text data to the “Description” host field(s) b. “Priority” to the “Priority Code:” host field c. “Responsibility Code” of the user d. Expiration Date” to the “Expiration Date” host field 3. Teller Alert passed to account in Navigator 4. Caution and Teller alert display in account profile in Connects
A66: Not Automated | B66: 18 | C66: RT.65 | D66: Medium | F66: Cautions | H66: Any SDB | I66: SDB Account Profile - Add New Teller Alert | J66: 1. Search Safe Deposit Box Account in Connects 2. View Account Profile in Connects | K66: 1. Validate Add is hidden on Cautions card for SDB
A67: Not Automated | B67: 18 | C67: RT.66 | D67: Medium | F67: Cautions | H67: Any Loan | I67: Loan Account Profile - Add New Cautiont | J67: 1. Search Loan Account in Connects 2. View Account Profile in Connects 3. Select "add" on Cautions Card 4. Add new Caution with an expiration date 5. View account in Navigator | K67: 1. Trashcan Icon hidden on cautions card 2. Hide "Caution Type" of "Teller Alerts" from drop down list box 3. Verify Caution exported as a miscellaneous addenda a. “Caution” text data to the “Description” host field(s) b. “Priority” to the “Priority Code:” host field c. “Responsibility Code” of the user d. Expiration Date” to the “Expiration Date” host field 4. Caution displays in account profile in Connects
A68: Not Automated | B68: 18 | C68: RT.67 | D68: Medium | F68: Cautions | H68: Any Test Client | I68: Client Profile - Port Addenda | J68: 1. Search Client in Connects as well as in Navigator with a client level and portfolio level addenda 2. View Client Profile in Connects, View portfolio level in Navigator | K68: 1. Miscellaneous addenda where "Priority Code = Priority" from portfolio level populated to "Cautions" on Client Profile 2. Miscellaneous addenda where "Priority Code = Priority" from client level populated to "Cautions" on Client Profile
A69: Not Automated | B69: 23 | C69: RT.68 | D69: High | F69: HSA Account Setup | H69: Individual HSA | I69: Validate Contribution Form Mapping | J69: 1. Create New HSA Account 2. Select Rollover Contribution 3. Select Previous Year 4. Complete Set Up 5. Validate Forms are Print Only and Mapping | K69: 1."Rollover from an HSA” checkbox mapped to HSA Contributions Instructions form and “HSA Custodial” form, section 2” 2. HSA Distribution form is generated with all fields completed 3. Validate POA form does not trigger 4. Validate Signature Card, Let's Get Started, Privacy Policy, Fee Schedule, TIS, HSA Contribution Instructions, HSA Custodial Account Organizer and HSA Distribution form are generated with all fields completed
A70: Not Automated | B70: 23 | C70: RT.69 | D70: High | F70: HSA Account Setup | H70: Individual HSA | I70: Document Manager | J70: 6. Choose Print and Print to PDF for test purposes | K70: 1. Validate Privacy Policy, Fee Schedule and TIS archive to Director
A71: Not Automated | B71: 23 | C71: RT.70 | D71: High | F71: HSA Account Setup | H71: Family HSA | I71: Validate Contribution Form Mapping | J71: 1. Create New HSA Account 2. Select Other contribution 3. Add one primary and four contingent beneficiaries a. “Beneficiaries” and “Contingent Beneficiaries” MUST total 100% each 4. Complete Set Up 5. Validate Forms are Print Only and Mapping | K71: 1. “Regular (including Catch-Up)” mapped to HSA Contributions Instructions form and “HSA Custodial” form, section 2 2. HSA Distribution form is generated with all fields completed 3. Validate POA form does not trigger 4. Validate Signature Card, Let's Get Started, Privacy Policy, Fee Schedule, TIS, HSA Contribution Instructions, HSA Custodial Account Organizer and HSA Distribution form are generated with all fields completed 5. Validate Beneficiary Data passes to form only, not host
... A81: Not Automated | B81: 27 | C81: RT.80 | D81: Medium | F81: EOD = 9 Restrictions | H81: Any Loan | I81: Loan - EOD code 9 Account (restricted) | J81: 1. Search client in Connects and Navigator that has a Loan with an EOD code of 9 2. In Connects client profile, review Details tab for EOD (Employee, officer, director) code | K81: 1. Graph Disabled 2. "Restricted" displayed within center of disabled graph 3. Validate related Accounts row for restricted account: a. Product Column - Display data, remove link (the Account Profile may not be accessed). b. Status Column - Display "Restricted" c. Balance Column - Display 'Restricted"
A82: Not Automated | B82: 31 | C82: RT.81 | D82: High | F82: CBRM | I82: Overdraft Settings | J82: 1. Search Product in Connects UI without overdraft selected in CBRM | K82: 1. Validate Overdraft Coverage Options window is not displayed in account set up or maintenance
A83: Not Automated | B83: 1 | C83: RT.82 | D83: High | F83: Address Enhancement | G83: Personal Client Setup | I83: Add New Seasonal Address | J83: 1. Create new Personal Client 2. Navigate to Communicate Preferences > Addresses 3. Add New Address that does not already exist on the core, using separate address for mailing vs. residential 4. Select "Add Seasonal Address" 5. Save changes and validate Navigator mapping | K83: 1. Address line 3 hidden 2. County label & DDLB hidden 3. Checkbox for "Add Seasonal Address" displayed & defaulted to unselected 4. Editable fields below displayed i. Country ii. Address (line 1) iii. Address (line 2) iv. Zip code with magnifying glass icon (standard Argo functionality) v. City vi. State vii. Start Date with calendar icon viii. End Date with calendar icon 5. Mailing address mapped to customer's tax reporting address in Nav
A84: Not Automated | B84: 1 | C84: RT.83 | D84: High | F84: Address Enhancement | G84: Personal Client Maintenance | I84: Personal Client Maintenance > Address | J84: 1. Search existing personal Client with seasonal address 2. Navigate to Communicate Preferences > Addresses 3. Validate only Seasonal address can be modified 4. Modify seasonal and save changes 5. Navigate to Document Manager and validate no Documents generated 6. Validate Navigator Mapping | K84: 1. All details of "Address Record" displayed within address grid 2. Modify button displayed 3. Seasonal address can be modified 4. Residential / Mailing address cannot be modified in this screen 5. Start and End dates displayed in MM/DD format (not YYYY) 6. Original record was modified, and no new records were created
A85: Not Automated | B85: 1 | C85: RT.84 | D85: High | F85: Address Enhancement | G85: Business Client Setup | I85: Add New Seasonal Address | J85: 1. Create new Business Client with another client in session 2. Navigate to Addresses 3. Add New Street and Mailing address using two different addresses - use the other customer in session to prefill the mailing address 4. Complete client setup 5. Validate Navigator mapping | K85: 1. Validate Mailing address maps to tax reporting address on the client record 2. Validate Street Address mapped as "Business Address" and Mailing Address mapped as "Mailing Address" 3. Validate the address record for the mailing/tax reporting address is the same address record as the client it was prefilled from, and a new address record was not created for mailing/tax reporting
A86: Not Automated | B86: 1 | C86: RT.85 | D86: High | F86: Address Enhancement | G86: Business Client Maintenance | I86: Business Client Maintenance > Address | J86: 1. Search Client 2. Add new Foreign Address, complete process 3. Navigate to Document Manager and validate Customer Information Change form generated with customer information, previous address, new address and tax reporting fields populated 4. Validate Navigator Mapping | K86: 1. Street/PO box displayed (instead of Address) and field is required 2. City, Province/Territory/Postal Code" displayed instead of address line 2 and field is required 3. Address line 3, Zip Code, City, State hidden 4. Helper text to the right of " City, Province/Territory/Postal Code" stating "“City, Province/Territory/Postal Code = City or Town name, other principal subdivision (i.e. Province, State, Country, etc.) and Postal Code (if known). Note: In some countries, the postal code may precede the city or town name” 5. Street/PO Box maps to Address Line 1 in Nav 6. City, Province/Territory/Postal Code data maps to Address Line 2 in Nav 7. Mailing address mapped to Tax Reporting in Nav
A87: Not Automated | B87: 1 | C87: RT.86 | D87: High | F87: Address Enhancement | G87: Account Setup | H87: Any DDA Product | I87: Validate Address verification against core. Matching Primary and Seasonal Addresses | J87: 1. Create New Account with existing Primary and Seasonal addresses on Nav 2. Navigate to Add Seasonal Address 3. Add new Address matching existing address on multiple records on Nav 4. Select address from modal window | K87: 1. "Multiple Records on File" Modal Window displayed 2. Address Window displayed selected address information 3. No new address record added to the host
A88: Not Automated | B88: 1 | C88: RT.87 | D88: High | F88: Address Enhancement | G88: Account Setup | H88: Any SAV Product | I88: Validate Address verification against core. | J88: 1. Create New Account with existing address on Nav 2. Navigate to Add Address 3. Add new Address matching one existing address on Nav (1 to 1 Match) 4. Select Process (Previous, Next, left hand Nav), complete update | K88: 1. Able to continue w/no interruption (multiple records on file modal window does not display) 2. No New Address Record added to the host
A89: Not Automated | B89: 1 | C89: RT.88 | D89: High | F89: Address Enhancement | G89: Account Maintenance | H89: Any DDA Product | I89: Add Seasonal Address | J89: 1. Search existing account 2. Navigate to "Update Account Info" > "Address Information" 3. Select Modify on existing address 4. Check "add seasonal address" checkbox 5. Navigate to Document Manager and validate no Documents generated 6. Validate Navigator Mapping | K89: 1. Address Type Displays as Mailing 2. Address line 3, Country lable/list box hidden 3. Add Seasonal Address Checkbox displayed 4. When selected, Fields below display a. County, Address (line1) Address (line 2), Zip Code, City, State DDLB, Start date field with calendar option MM/DD format, End date with calendar option MM/DD format) 5. Validate no new address record added to the host and the existing address record was modified
A90: Not Automated | B90: 1 | C90: RT.89 | D90: High | F90: Address Enhancement | G90: Account Maintenance | H90: Any SAV Product | I90: Update Account Info > Address Info Section | J90: 1. Search existing SAV account 2. Navigate to "Update Account Info" > "Address Information" 2. Remove existing address (trashcan icon) 3. Select Add Address and enter address with multiple matching record currently existing in Nav a. Select existing address record 4. Navigate to Document Manager and validate Customer Information Change form generated with account number, previous address, and new address populated 5. Validate Navigator Mapping | K90: 1. Address Type Displays as Mailing 2. Address line 3, Country label/list box hidden 3. Add Seasonal Address Checkbox displayed 4. Validate USPS validation NOT presented 5. Validate new address record NOT created in Nav
A91: Not Automated | B91: 1 | C91: RT.90 | D91: High | F91: Address Enhancement | G91: Account Maintenance | H91: Any CD Product | I91: Update Account Info > Address Info Section | J91: 1. Search existing CD account 2. Navigate to "Update Account Info" > "Address Information" 2. Remove existing address (trashcan icon) 3. Select Add Address and enter address with multiple matching record currently existing in Nav a. Select existing address record 4. Navigate to Document Manager and validate Customer Information Change form generated with account number, previous address, and new address populated 5. Validate Navigator Mapping | K91: 1. Address Type Displays as Mailing 2. Address line 3, Country label/list box hidden 3. Add Seasonal Address Checkbox displayed 4. Validate USPS validation NOT presented 5. Validate new address record NOT created in Nav
A92: Not Automated | B92: 1 | C92: RT.91 | D92: High | F92: Address Enhancement | G92: Account Maintenance | H92: Any SDB Product | I92: Update Account Info > Address Info Section | J92: 1. Search existing SDB account 2. Navigate to "Update Account Info" > "Address Information" 2. Remove existing address (trashcan icon) 3. Select Add Address and enter address/seasonal with one matching record currently existing in Nav | K92: 1. Address Type Displays as Mailing 2. Address line 3, Country lable/list box hidden 3. Add Seasonal Address Checkbox displayed 4. When selected, Fields below display a. County, Address (line1) Address (line 2), Zip Code, City, State DDLB, Start date field with calendar option MM/DD format, End date with calendar option MM/DD format) 5. Validate address is changed without interruption to the user 6. Validate new address record NOT created in Nav
A93: Not Automated | B93: 10 | C93: RT.92 | D93: High | F93: IRA Setup | G93: Account Setup | H93: IRA Savings - | I93: Open IRA Savings product for individual existing customer - use CBRM configuration of Prior year within cutoff date | J93: 1. Select one existing customer with last name of "Customer", ownership on DDA accounts and DOB = client is 73 or older and pull into session. 2. Select Product Search 3. Select IRA 4. Choose IRA Savings Product | K93: Validate product is available to add.
A94: Not Automated | B94: 10 | C94: RT.93 | D94: High | F94: IRA Setup | G94: Account Setup | H94: IRA Savings - | I94: Ownership Page | J94: 5. Choose individual from ownership ddlb and select client from session 6. Select facsimile signature checkbox | K94: 1. Validate Branch and region match sign on information
A95: Not Automated | B95: 10 | C95: RT.94 | D95: High | F95: IRA Setup | G95: Account Setup | H95: IRA Savings - | I95: Detail Page | J95: 1. IRA Type - Select Traditional/Individual 2. Verify the individual owner is listed in the account titling under name line 1 | K95: 1. Validate Rate and APY fields are read only and disabled and are correct compared to the current region BPM 2. Validate Tax Liability Information displays correctly and withholding reason label and DDLB are hidden in Tax Liability box
A96: Not Automated | B96: 10 | C96: RT.95 | D96: High | F96: IRA Setup | G96: Account Setup | H96: IRA Savings - | I96: Detail Page - Contributions Section | J96: 1. Select Prior Year and validate Tax Year changes to previous year 2. Select Contribution Types of Rollover from a Traditional IRA, Rollover from an Eligible Retirement Plan and Direct Rollover from an Eligible Retirement Plan a. Validate when any of these three are selected, required "Contribution Check Date" field displays to the right of the "Contribution Type" DDLB. 3. Select Contribution type of "Transfer from a Traditional IRA" a. Validate new "Request funds from another institution" question displays with no default b. Select Yes and validate the following is displayed i. Required "Institution Name" field - enter other bank's name ii. Required "Address" field - enter test address iii. Required "IRA Account Number" field - enter test account number iv. Required "Full Balance?" field defaulted to Yes 4. Change Contribution Type to Rollover from Traditional IRA 5. Contribution Check Date - Enter date greater than 60 days from the current date | K96: 1. Validate the Contribution Type dropdown contains the following: a. Blank (default) b. Regular c. Catch-Up (age 50 and older) d. Rollover from a Traditional IRA e. Rollover from an Eligible Retirment Plan f. Direct Rollover from an Eligible-Retirement Plan g. Transfer from a Traditional IRA h. Recharacterization
A97: Not Automated | B97: 10 | C97: RT.96 | D97: High | F97: IRA Setup | G97: Account Setup | H97: IRA Savings - | I97: Detail Page - Distribution Section | J97: 1. "Scheduled Required Minimum Distribution" displays with required Y/N radio buttons - choose Yes | K97: 1. Validate Required Minimum Distribution LHN displays
A98: Not Automated | B98: 10 | C98: RT.97 | D98: High | F98: IRA Setup | G98: Account Setup | H98: IRA Savings - | I98: Required Minimum Distribution Page | J98: 1. Distribution Method - choose Transfer to Account a. Validate Bank and Type labels are hidden and Find Account link displays to the right of the Number field b. Select link and validate only accounts client is an owner/signer on display c. Select a Checking account 2. Validate RMD Only has no default and is required - choose "Yes" 3. Payment Start Date - enter the 15th of the current month and validate error message displays a. Icon = ! b. Title = Date Error c. Text = Payment Start Date cannot be within the current month" d. OK button removes the date from the payment start date field 4. Payment Frequency - choose Quarterly | K98: 1. Validate page header is labeled "Required Minimum Distribution" 2. Validate "Distribution Reason" DDLB is defaulted to "Normal (59 1/2 or older) and is read only 3. Validate Payment Election Option field is defaulted to "Periodic" and is read only and disabled 4. Validate Payment Frequency DDLB option is "Annually" instead of "Annually/At Maturity" 5. Validate text of "Preferred RMD dates are days of the month between the 15th and 28th of the month" displays to the right of the "Payment Start Date" field and Calendar icon is hidden 6. Validate "10% + Additional Amount" label is hidden 7. Validate Distribution Detail header and fields are hidden
... A100: Not Automated | B100: 10 | C100: RT.99 | D100: High | F100: IRA Setup | G100: Account Setup | H100: IRA Savings - | I100: Address Page | J100: 1. Select Next 2. Prefill from ddlb should have name record mailing address listed 3. Select mailing address from ddlb 4. Click Next | K100: 1. Validate address prefilled as customer address shows on name record
A101: Not Automated | B101: 10/36 | C101: RT.100 | D101: High | F101: IRA Setup | G101: Account Setup | H101: IRA Savings - | I101: Services Page | J101: 1. Validate Online Banking is in "Add Services" box. a. Choose "Remove" for Online Banking to take it out of Add Services
A102: Not Automated | B102: 10 | C102: RT.101 | D102: High | F102: IRA Setup | G102: Account Setup | H102: IRA Savings - | I102: Disclosure Page | J102: 1. Review Document Viewer window 2. Choose Next | K102: 1. Validate Disclosure left-hand navigation displays the following in Document Viewer: a. "Availability of Funds Disclosure" b. IRA Savings "Truth-in-Savings" with the following fields mapped: i. Date Opened/As of = current Date ii. Customer Name = For Informational Purposes Only iii. Account Number = Blank iv. Product = IRA Savings v. Rate and APY match to the current rate sheet for the region (APY rounded up to two decimal places)
A103: Not Automated | B103: 10 | C103: RT.102 | D103: High | F103: IRA Setup | G103: Account Setup | H103: IRA Savings - | I103: Due Diligence Page | J103: 1. Review the Patriot Act disclosure and click close 2. What is the purpose of this account: choose Personal 3. What is the source of the funds used to establish the account - select Employment Income | K103: 1. Disclosure message should appear and close. 2. Purpose of account contains: Personal, Family, Household, Savings, Retirement, Personal Investment 3. Source of funds contain: Employment Income, Inheritance, Savings, Retirement
A104: Not Automated | B104: 10 | C104: RT.103 | D104: High | F104: IRA Setup | G104: Account Setup | H104: IRA Savings - | I104: Portfolio Page | J104: 1. Select Portfolio 2. Click Process. | K104: Account should show on existing customer portfolio used for testing
A105: Not Automated | B105: 10 | C105: RT.104 | D105: High | F105: IRA Setup | G105: Account Setup | H105: IRA Savings - | I105: Document Manager | J105: 1. Click on document manager and open the account set up option to view available documents 2. Select Print all selected - Print to PDF for testing purposes 3. End Session | K105: 1. Validate Required Minimum Distribution, IRA Custodial Organizer, IRA Financial Disclosure, FNB Lets get started, Privacy Policy, Personal Fee Schedule, Deposit Account Agreement, Signature Card, Facsimile Signature Agreement and TIS are all that generated and are populated with proper account information a. Validate "Postponed Contribution/Late Rollover (including with self-certification)" and "Transfer" are selected under Contribution Information on the IRA Application b. Validate all documents are print only and E-Sign not available 2. Validate all documents printed and TIS, Privacy Policy, Fee Schedule, and Deposit Account Agreement were archived to Director 3. Signature Card is print only due to facsimile signature and facsimile signature checkbox is selected on signature card 4. Validate all forms generated/fields mapped (including rate on TIS) to same product in BPM
A106: Not Automated | B106: 10 | C106: RT.105 | D106: High | F106: IRA Setup | G106: Account Setup | H106: IRA Savings - | I106: Navigator | J106: 1. Review product specs and mapping | K106: 1. Interest cycle, correct statement cycle, current date mapped to date opened - SEND TO DEPOSIT OPS FOR VALIDATION 2. 1 passed to Reg CC Exception Code, 12/31/2172 passed to Reg CC Expiration Date 3. Account type code is 100 4. Due Diligence answers mapped to flex fields 5. 01 mapped to IRA Plan field 6. Validate IRA owner mapped as tax reporting, owner/signer and Indiv/Single/Sole Owner
A107: Not Automated | B107: 10 | C107: RT.106 | D107: High | F107: IRA Setup | G107: Account Setup | H107: IRA Savings - | I107: Disclosure Database | J107: 1. Request "Consumer_Event" table screenshot by providing the account number to Business Systems Analysis (Joe Renfro, Jason Miller, etc.). | K107: 1. Validate the following was written to the Consumer_Event table in the Argo database: a. Account Number b. Time (in seconds) c. Date e. event_desc = "New Account Disclosures"
A108: Not Automated | B108: 10 | C108: RT.107 | D108: High | F108: IRA Setup | G108: Account Setup | H108: IRA Savings - | I108: Open IRA Savings product for individual existing customer - use CBRM configuration of Prior year within cutoff date | J108: 1. Select one existing customer with last name of "Customer", ownership on DDA accounts and DOB = client is 72 and has already had their birthday in the current calendar year and pull into session. 2. Select Product Search 3. Select IRA 4. Choose IRA Savings Product | K108: Validate product is available to add.
A109: Not Automated | B109: 10 | C109: RT.108 | D109: High | F109: IRA Setup | G109: Account Setup | H109: IRA Savings - | I109: Ownership Page | J109: 5. Choose individual from ownership ddlb and select client from session | K109: 1. Validate Branch and region match sign on information
A110: Not Automated | B110: 10 | C110: RT.109 | D110: High | F110: IRA Setup | G110: Account Setup | H110: IRA Savings - | I110: Detail Page | J110: 1. IRA Type - Select SEP/Employer Plan 2. Verify the individual owner is listed in the account titling under name line 1 | K110: 1. Validate Rate and APY fields are read only and disabled and are correct compared to the current rate sheet as of D1QA1 date 2. Validate Tax Liability Information displays correctly and withholding reason label and DDLB are hidden in Tax Liability box
A111: Not Automated | B111: 10 | C111: RT.110 | D111: High | F111: IRA Setup | G111: Account Setup | H111: IRA Savings - | I111: Detail Page - Contributions Section | J111: 1. Select Current Year 2. Select Contribution Types - Select Transfer from a Traditional IRA a. Validate new "Request funds from another institution" question displays with no default b. Select Yes and validate the following is displayed i. Required "Institution Name" field - enter other bank's name ii. Required "Address" field - enter test address iii. Required "IRA Account Number" field - enter test account number iv. Required "Full Balance?" field defaulted to Yes - choose No, validate required Amount field displays and enter an amount | K111: 1. Validate the Contribution Type dropdown contains the following: a. Blank (default) b. Regular c. Catch-Up (age 50 and older) d. Rollover from a Traditional IRA e. Rollover from an Eligible Retirment Plan f. Direct Rollover from an Eligible-Retirement Plan g. Transfer from a Traditional IRA h. Recharacterization 2. Validate the RMD section is hidden
A112: Not Automated | B112: 10 | C112: RT.111 | D112: High | F112: IRA Setup | G112: Account Setup | H112: IRA Savings - | I112: Beneficiaries Page | J112: 1. Select Next and select Add 2. Choose the search link to search for a name record that does not contain a tax ID number 3. Add one primary and four contingent beneficiaries | K112: 1. Validate Tax ID Number is not required 2. Validate "Type" DDLB contains "Primary" and "Contingent"
A113: Not Automated | B113: 10 | C113: RT.112 | D113: High | F113: IRA Setup | G113: Account Setup | H113: IRA Savings - | I113: Address Page | J113: 1. Select Next 2. Prefill from ddlb should have name record mailing address listed 3. Select mailing address from ddlb 4. Click Next | K113: 1. Validate address prefilled as customer address shows on name record
A114: Not Automated | B114: 10 | C114: RT.113 | D114: High | F114: IRA Setup | G114: Account Setup | H114: IRA Savings - | I114: Disclosure Page | J114: 1. Review Document Viewer window 2. Choose Next | K114: 1. Validate Disclosure left-hand navigation displays the following in Document Viewer: a. "Availability of Funds Disclosure" b. IRA Savings "Truth-in-Savings" with the following fields mapped: i. Date Opened/As of = current Date ii. Customer Name = For Informational Purposes Only iii. Account Number = Blank iv. Product = IRA Savings v. Rate and APY match to the current rate sheet for the region (APY rounded up to two decimal places)
A115: Not Automated | B115: 10 | C115: RT.114 | D115: High | F115: IRA Setup | G115: Account Setup | H115: IRA Savings - | I115: Services Page | J115: 1. Validate Online Banking is in "Add Services" box. a. Choose "Remove" for Online Banking to take it out of Add Services
A116: Not Automated | B116: 10 | C116: RT.115 | D116: High | F116: IRA Setup | G116: Account Setup | H116: IRA Savings - | I116: Due Diligence Page | J116: 1. Review the Patriot Act disclosure and click close 2. What is the purpose of this account: choose Savings 3. What is the source of the funds used to establish the account - select Retirement | K116: 1. Disclosure message should appear and close. 2. Purpose of account contains: Personal, Family, Household, Savings, Retirement, Personal Investment 3. Source of funds contain: Employment Income, Inheritance, Savings, Retirement
A117: Not Automated | B117: 10 | C117: RT.116 | D117: High | F117: IRA Setup | G117: Account Setup | H117: IRA Savings - | I117: Portfolio Page | J117: 1. Select Portfolio 2. Click Process. | K117: Account should show on existing customer portfolio used for testing
A118: Not Automated | B118: 10 | C118: RT.117 | D118: High | F118: IRA Setup | G118: Account Setup | H118: IRA Savings - | I118: Document Manager | J118: 1. Click on document manager and open the account set up option to view available documents 2. Select Print all selected - Print to PDF for testing purposes 3. End Session | K118: 1. Validate IRA Custodial Organizer, Request for Transfer or Conversion to an IRA for Traditional, Roth, and Simple IRA, IRA Financial Disclosure, FNB Lets get started, Privacy Policy, Personal Fee Schedule, Deposit Account Agreement, Signature Card and TIS are all that generated and are populated with proper account information a. Validate "Simplified Employee Pension" checkbox is selected on "Traditional IRA Application" form and "Transfer" checkbox is selected. b. Validate all documents are print only and E-Sign not available 2. Validate all documents printed and TIS, Privacy Policy, Fee Schedule, and Deposit Account Agreement were archived to Director a. Privacy Policy archived to "Privacy Policy" b. Fee schedule archived to "Fee Schedule" c. TIS archived to "Truth in Savings" d. Deposit Account Agreement archived to "FNB Deposit Account Agreement" 3. Validate rate on TIS matches rate sheet as of D1QA1 Date
A119: Not Automated | B119: 10 | C119: RT.118 | D119: High | F119: IRA Setup | G119: Account Setup | H119: IRA Savings - | I119: Navigator | J119: 1. Review product specs and mapping | K119: 1. Interest cycle, correct statement cycle, current date mapped to date opened - SEND TO DEPOSIT OPS FOR VALIDATION 2. 1 passed to Reg CC Exception Code, 12/31/2172 passed to Reg CC Expiration Date 3. Account type code is 100 4. Due Diligence answers mapped to flex fields 5. 03 mapped to IRA Plan field 6. Validate IRA owner mapped as tax reporting, owner/signer and Indiv/Single/Sole Owner
A120: Not Automated | B120: 10 | C120: RT.119 | D120: High | F120: IRA Setup | G120: Account Setup | H120: 6-11 MO IRA CD - | I120: Open IRA CD product for individual existing customer - use CBRM configuration of Prior year outside of cutoff date | J120: 1. Select one existing customer with last name of "Customer", ownership on DDA accounts and DOB = client is 72 and their birthday has not occurred yet for the calendar year and pull into session. a. Add a second client to session to use as a beneficiary so that Prefill From can be selected, and a third client to use as POA 2. Select Product Search 3. Select IRA 4. Choose IRA 6-11 MO Product | K120: Validate product is available to add.
A121: Not Automated | B121: 10 | C121: RT.120 | D121: High | F121: IRA Setup | G121: Account Setup | H121: 6-11 MO IRA CD - | I121: Ownership Page | J121: 5. Choose individual from ownership ddlb and select client from session 6. Add Power of Attorney to account | K121: 1. Validate Branch and region match sign on information
A122: Not Automated | B122: 10 | C122: RT.121 | D122: High | F122: IRA Setup | G122: Account Setup | H122: 6-11 MO IRA CD - | I122: Detail Page | J122: 1. IRA Type - Select Traditional/Individual 2. Verify the individual owner is listed in the account titling under name line 1 3. Choose Discretionary Rate Bump, validate rate is bumped by .05 and new rate and APY are correct | K122: 1. Validate Rate and APY fields are read only and disabled and are correct compared to the current region BPM 2. Validate Tax Liability Information displays correctly and withholding reason label and DDLB are hidden in Tax Liability box
A123: Not Automated | B123: 10 | C123: RT.122 | D123: High | F123: IRA Setup | G123: Account Setup | H123: 6-11 MO IRA CD - | I123: Detail Page | J123: 1. Issue Value - Enter $50, after validating $500 minimum is required, enter $1000.75 2. Enter 6 months as the term | K123: 1. Validate $50 is rejected 2. Validate no Promos are available 3. Validate Term field accepts all values within the term, i.e., 3-5 month would accept 3,4, and 5 months, but 2 and 6 would be rejected 4. Validate Maturity Option is "Auto Renewal" (read only and disabled) and Maturity Date is read only and disabled.
...

Sheet CR Automation Summary
A1: CR Related | B1: Automated | C1: Blocked | D1: Cancelled | E1: Not Automated | F1: Total
A2: 1 | B2: =COUNTIFS('Automation Regression Test Plan'!B:B,A2,'Automation Regression Test Plan'!A:A,"Automation") -> 0 | C2: =COUNTIFS('Automation Regression Test Plan'!B:B,A2,'Automation Regression Test Plan'!A:A,"Blocked") -> 0 | D2: =COUNTIFS('Automation Regression Test Plan'!B:B,A2,'Automation Regression Test Plan'!A:A,"Cancelled") -> 0 | E2: =COUNTIFS('Automation Regression Test Plan'!B:B,A2,'Automation Regression Test Plan'!A:A,"Not Automated") -> 10 | F2: 10
A3: 10 | B3: =COUNTIFS('Automation Regression Test Plan'!B:B,A3,'Automation Regression Test Plan'!A:A,"Automation") -> 0 | C3: =COUNTIFS('Automation Regression Test Plan'!B:B,A3,'Automation Regression Test Plan'!A:A,"Blocked") -> 0 | D3: =COUNTIFS('Automation Regression Test Plan'!B:B,A3,'Automation Regression Test Plan'!A:A,"Cancelled") -> 0 | E3: =COUNTIFS('Automation Regression Test Plan'!B:B,A3,'Automation Regression Test Plan'!A:A,"Not Automated") -> 70 | F3: 70
A4: 10/36 | B4: =COUNTIFS('Automation Regression Test Plan'!B:B,A4,'Automation Regression Test Plan'!A:A,"Automation") -> 0 | C4: =COUNTIFS('Automation Regression Test Plan'!B:B,A4,'Automation Regression Test Plan'!A:A,"Blocked") -> 0 | D4: =COUNTIFS('Automation Regression Test Plan'!B:B,A4,'Automation Regression Test Plan'!A:A,"Cancelled") -> 0 | E4: =COUNTIFS('Automation Regression Test Plan'!B:B,A4,'Automation Regression Test Plan'!A:A,"Not Automated") -> 1 | F4: 1
A5: 11 | B5: =COUNTIFS('Automation Regression Test Plan'!B:B,A5,'Automation Regression Test Plan'!A:A,"Automation") -> 0 | C5: =COUNTIFS('Automation Regression Test Plan'!B:B,A5,'Automation Regression Test Plan'!A:A,"Blocked") -> 0 | D5: =COUNTIFS('Automation Regression Test Plan'!B:B,A5,'Automation Regression Test Plan'!A:A,"Cancelled") -> 0 | E5: =COUNTIFS('Automation Regression Test Plan'!B:B,A5,'Automation Regression Test Plan'!A:A,"Not Automated") -> 8 | F5: 8
A6: 13 | B6: =COUNTIFS('Automation Regression Test Plan'!B:B,A6,'Automation Regression Test Plan'!A:A,"Automation") -> 0 | C6: =COUNTIFS('Automation Regression Test Plan'!B:B,A6,'Automation Regression Test Plan'!A:A,"Blocked") -> 0 | D6: =COUNTIFS('Automation Regression Test Plan'!B:B,A6,'Automation Regression Test Plan'!A:A,"Cancelled") -> 0 | E6: =COUNTIFS('Automation Regression Test Plan'!B:B,A6,'Automation Regression Test Plan'!A:A,"Not Automated") -> 13 | F6: 13
A7: 15 | B7: =COUNTIFS('Automation Regression Test Plan'!B:B,A7,'Automation Regression Test Plan'!A:A,"Automation") -> 0 | C7: =COUNTIFS('Automation Regression Test Plan'!B:B,A7,'Automation Regression Test Plan'!A:A,"Blocked") -> 0 | D7: =COUNTIFS('Automation Regression Test Plan'!B:B,A7,'Automation Regression Test Plan'!A:A,"Cancelled") -> 0 | E7: =COUNTIFS('Automation Regression Test Plan'!B:B,A7,'Automation Regression Test Plan'!A:A,"Not Automated") -> 4 | F7: 4
A8: 18 | B8: =COUNTIFS('Automation Regression Test Plan'!B:B,A8,'Automation Regression Test Plan'!A:A,"Automation") -> 0 | C8: =COUNTIFS('Automation Regression Test Plan'!B:B,A8,'Automation Regression Test Plan'!A:A,"Blocked") -> 0 | D8: =COUNTIFS('Automation Regression Test Plan'!B:B,A8,'Automation Regression Test Plan'!A:A,"Cancelled") -> 0 | E8: =COUNTIFS('Automation Regression Test Plan'!B:B,A8,'Automation Regression Test Plan'!A:A,"Not Automated") -> 9 | F8: 9
A9: 2 | B9: =COUNTIFS('Automation Regression Test Plan'!B:B,A9,'Automation Regression Test Plan'!A:A,"Automation") -> 0 | C9: =COUNTIFS('Automation Regression Test Plan'!B:B,A9,'Automation Regression Test Plan'!A:A,"Blocked") -> 0 | D9: =COUNTIFS('Automation Regression Test Plan'!B:B,A9,'Automation Regression Test Plan'!A:A,"Cancelled") -> 0 | E9: =COUNTIFS('Automation Regression Test Plan'!B:B,A9,'Automation Regression Test Plan'!A:A,"Not Automated") -> 1 | F9: 1
A10: 20 | B10: =COUNTIFS('Automation Regression Test Plan'!B:B,A10,'Automation Regression Test Plan'!A:A,"Automation") -> 0 | C10: =COUNTIFS('Automation Regression Test Plan'!B:B,A10,'Automation Regression Test Plan'!A:A,"Blocked") -> 0 | D10: =COUNTIFS('Automation Regression Test Plan'!B:B,A10,'Automation Regression Test Plan'!A:A,"Cancelled") -> 0 | E10: =COUNTIFS('Automation Regression Test Plan'!B:B,A10,'Automation Regression Test Plan'!A:A,"Not Automated") -> 53 | F10: 53
A11: 23 | B11: =COUNTIFS('Automation Regression Test Plan'!B:B,A11,'Automation Regression Test Plan'!A:A,"Automation") -> 0 | C11: =COUNTIFS('Automation Regression Test Plan'!B:B,A11,'Automation Regression Test Plan'!A:A,"Blocked") -> 0 | D11: =COUNTIFS('Automation Regression Test Plan'!B:B,A11,'Automation Regression Test Plan'!A:A,"Cancelled") -> 0 | E11: =COUNTIFS('Automation Regression Test Plan'!B:B,A11,'Automation Regression Test Plan'!A:A,"Not Automated") -> 25 | F11: 25
A12: 24 | B12: =COUNTIFS('Automation Regression Test Plan'!B:B,A12,'Automation Regression Test Plan'!A:A,"Automation") -> 0 | C12: =COUNTIFS('Automation Regression Test Plan'!B:B,A12,'Automation Regression Test Plan'!A:A,"Blocked") -> 0 | D12: =COUNTIFS('Automation Regression Test Plan'!B:B,A12,'Automation Regression Test Plan'!A:A,"Cancelled") -> 0 | E12: =COUNTIFS('Automation Regression Test Plan'!B:B,A12,'Automation Regression Test Plan'!A:A,"Not Automated") -> 2 | F12: 2
A13: 24/7 | B13: =COUNTIFS('Automation Regression Test Plan'!B:B,A13,'Automation Regression Test Plan'!A:A,"Automation") -> 0 | C13: =COUNTIFS('Automation Regression Test Plan'!B:B,A13,'Automation Regression Test Plan'!A:A,"Blocked") -> 0 | D13: =COUNTIFS('Automation Regression Test Plan'!B:B,A13,'Automation Regression Test Plan'!A:A,"Cancelled") -> 0 | E13: =COUNTIFS('Automation Regression Test Plan'!B:B,A13,'Automation Regression Test Plan'!A:A,"Not Automated") -> 2 | F13: 2
... A44: Product Search | B44: =COUNTIFS('Automation Regression Test Plan'!B:B,A44,'Automation Regression Test Plan'!A:A,"Automation") -> 0 | C44: =COUNTIFS('Automation Regression Test Plan'!B:B,A44,'Automation Regression Test Plan'!A:A,"Blocked") -> 0 | D44: =COUNTIFS('Automation Regression Test Plan'!B:B,A44,'Automation Regression Test Plan'!A:A,"Cancelled") -> 0 | E44: =COUNTIFS('Automation Regression Test Plan'!B:B,A44,'Automation Regression Test Plan'!A:A,"Not Automated") -> 10 | F44: 10
A45: Total Test Cases | B45: =SUBTOTAL(9,B2:B44) -> 1140 | C45: =SUBTOTAL(9,C2:C44) -> 33 | D45: =SUBTOTAL(9,D2:D44) -> 8 | E45: =SUBTOTAL(9,E2:E44) -> 1757 | F45: =SUBTOTAL(9,F2:F44) -> 2938
